MANIFEST.in
README.rst
setup.py
statio/__init__.py
statio/core.py
statio.egg-info/PKG-INFO
statio.egg-info/SOURCES.txt
statio.egg-info/dependency_links.txt
statio.egg-info/top_level.txt
statio/tests/test_core.py