Metadata-Version: 1.0
Name: statio
Version: 0.0.2
Summary: 
